{
  "cookies": [
    {
      "name": "wordpress_sec_13c4fe936d288f09250768a787153bb4",
      "value": "qa-utsav-patel%7C1707547444%7CWInaBahZiVFzuKpig4Vaf24JfQfE5symiYc1VMOvQTl%7Cfa5904b52b362d1fc0f3bc5c864f21bed4ad6530298435f646491aa1bd469de0",
      "domain": "qa-utsav-patel.rt.gw",
      "path": "/wp-content/plugins",
      "expires": -1,
      "httpOnly": true,
      "secure": true,
      "sameSite": "Lax"
    },
    {
      "name": "wordpress_sec_13c4fe936d288f09250768a787153bb4",
      "value": "qa-utsav-patel%7C1707547444%7CWInaBahZiVFzuKpig4Vaf24JfQfE5symiYc1VMOvQTl%7Cfa5904b52b362d1fc0f3bc5c864f21bed4ad6530298435f646491aa1bd469de0",
      "domain": "qa-utsav-patel.rt.gw",
      "path": "/wp-admin",
      "expires": -1,
      "httpOnly": true,
      "secure": true,
      "sameSite": "Lax"
    },
    {
      "name": "wordpress_test_cookie",
      "value": "WP%20Cookie%20check",
      "domain": "qa-utsav-patel.rt.gw",
      "path": "/",
      "expires": -1,
      "httpOnly": false,
      "secure": true,
      "sameSite": "Lax"
    },
    {
      "name": "wordpress_logged_in_13c4fe936d288f09250768a787153bb4",
      "value": "qa-utsav-patel%7C1707547444%7CWInaBahZiVFzuKpig4Vaf24JfQfE5symiYc1VMOvQTl%7Cfbfad177b0da0764a00b8f81b1ac7054ddfdb30493b975e2ca800e4be66eb215",
      "domain": "qa-utsav-patel.rt.gw",
      "path": "/",
      "expires": -1,
      "httpOnly": true,
      "secure": true,
      "sameSite": "Lax"
    },
    {
      "name": "wp-settings-time-2",
      "value": "1707374645",
      "domain": "qa-utsav-patel.rt.gw",
      "path": "/",
      "expires": 1738910645.250035,
      "httpOnly": false,
      "secure": true,
      "sameSite": "Lax"
    }
  ],
  "origins": []
}